pygcal/__init__.py
pygcal/client_secret.json
pygcal/configs.py
pygcal/constants.py
pygcal/main.py
pygcal/static.py
pygcal-0.0.7.dist-info/licenses/LICENSE
pygcal-0.0.7.dist-info/METADATA
pygcal-0.0.7.dist-info/WHEEL
pygcal-0.0.7.dist-info/entry_points.txt
pygcal-0.0.7.dist-info/top_level.txt
pygcal-0.0.7.dist-info/RECORD
